[
  {
    "id": "cbse_c10_math_imp_001",
    "question": "The altitude of a right triangle is 7 cm less than its base. If the hypotenuse is 13 cm, find the other two sides.",
    "subject": "mathematics",
    "class": 10,
    "year": null,
    "frequency": "high",
    "appeared_in_years": [
      2018,
      2019,
      2021,
      2022
    ],
    "chapter": "Quadratic Equations",
    "topic": "word problems вЂ“ geometry",
    "marks": 3,
    "type": "SA",
    "board": "CBSE",
    "answer": "Let base = x cm, altitude = (x в€’ 7) cm. By Pythagoras: xВІ + (xв€’7)ВІ = 13ВІ в†’ 2xВІ в€’ 14x + 49 = 169 в†’ 2xВІ в€’ 14x в€’ 120 = 0 в†’ xВІ в€’ 7x в€’ 60 = 0 в†’ (x в€’ 12)(x + 5) = 0. Since x > 0, x = 12. Base = 12 cm, Altitude = 5 cm.",
    "source": "practice"
  },
  {
    "id": "cbse_c10_math_imp_002",
    "question": "Two water taps together can fill a tank in 9в…њ hours. The tap with larger diameter takes 10 hours less than the smaller one to fill the tank. Find the time in which each tap can separately fill the tank.",
    "subject": "mathematics",
    "class": 10,
    "year": null,
    "frequency": "high",
    "appeared_in_years": [
      2017,
      2019,
      2020,
      2023
    ],
    "chapter": "Quadratic Equations",
    "topic": "word problems вЂ“ work and time",
    "marks": 4,
    "type": "LA",
    "board": "CBSE",
    "answer": "Let smaller tap take x hours, larger takes (xв€’10) hours. 1/x + 1/(xв€’10) = 8/75 в†’ 75(2xв€’10) = 8x(xв€’10) в†’ 8xВІ в€’ 230x + 750 = 0 в†’ 4xВІ в€’ 115x + 375 = 0 в†’ (xв€’25)(4xв€’15) = 0. x = 25 (since x = 15/4 < 10 is not valid). Smaller tap: 25 hours, Larger tap: 15 hours.",
    "source": "practice"
  },
  {
    "id": "cbse_c10_math_imp_003",
    "question": "A train travels 360 km at a uniform speed. If the speed had been 5 km/h more, it would have taken 1 hour less for the same journey. Find the speed of the train.",
    "subject": "mathematics",
    "class": 10,
    "year": null,
    "frequency": "high",
    "appeared_in_years": [
      2016,
      2018,
      2019,
      2022
    ],
    "chapter": "Quadratic Equations",
    "topic": "word problems вЂ“ speed, distance, time",
    "marks": 4,
    "type": "LA",
    "board": "CBSE",
    "answer": "Let speed = x km/h. 360/x в€’ 360/(x+5) = 1 в†’ 360(x+5) в€’ 360x = x(x+5) в†’ 1800 = xВІ + 5x в†’ xВІ + 5x в€’ 1800 = 0 в†’ (x + 45)(x в€’ 40) = 0. x = 40 km/h.",
    "source": "practice"
  },
  {
    "id": "cbse_c10_math_imp_004",
    "question": "Find the values of k for which the quadratic equation kx(x в€’ 2) + 6 = 0 has two equal real roots.",
    "subject": "mathematics",
    "class": 10,
    "year": null,
    "frequency": "high",
    "appeared_in_years": [
      2014,
      2016,
      2017,
      2019,
      2023
    ],
    "chapter": "Quadratic Equations",
    "topic": "nature of roots вЂ“ discriminant",
    "marks": 2,
    "type": "SA",
    "board": "CBSE",
    "answer": "kxВІ в€’ 2kx + 6 = 0. For equal roots, D = 0. bВІ в€’ 4ac = 0 в†’ 4kВІ в€’ 24k = 0 в†’ 4k(k в€’ 6) = 0. k = 0 or k = 6. Since k = 0 makes it non-quadratic, k = 6.",
    "source": "practice"
  },
  {
    "id": "cbse_c10_math_imp_005",
    "question": "The sum of the reciprocals of Rehman's ages 3 years ago and 5 years from now is 1/3. Find his present age.",
    "subject": "mathematics",
    "class": 10,
    "year": null,
    "frequency": "high",
    "appeared_in_years": [
      2015,
      2018,
      2020
    ],
    "chapter": "Quadratic Equations",
    "topic": "word problems вЂ“ ages",
    "marks": 3,
    "type": "SA",
    "board": "CBSE",
    "answer": "Let present age = x years. 1/(xв€’3) + 1/(x+5) = 1/3 в†’ 3(2x+2) = (xв€’3)(x+5) в†’ 6x + 6 = xВІ + 2x в€’ 15 в†’ xВІ в€’ 4x в€’ 21 = 0 в†’ (xв€’7)(x+3) = 0. x = 7 years.",
    "source": "practice"
  },
  {
    "id": "cbse_c10_math_imp_006",
    "question": "The first term of an AP is 5, the last term is 45 and the sum is 400. Find the number of terms and the common difference.",
    "subject": "mathematics",
    "class": 10,
    "year": null,
    "frequency": "high",
    "appeared_in_years": [
      2016,
      2018,
      2019,
      2021,
      2023
    ],
    "chapter": "Arithmetic Progressions",
    "topic": "nth term and sum formula",
    "marks": 3,
    "type": "SA",
    "board": "CBSE",
    "answer": "Sв‚™ = n/2(a + l) в†’ 400 = n/2(5 + 45) в†’ n = 16. aв‚™ = a + (nв€’1)d в†’ 45 = 5 + 15d в†’ d = 8/3. No. of terms = 16, d = 8/3.",
    "source": "practice"
  },
  {
    "id": "cbse_c10_math_imp_007",
    "question": "How many three-digit numbers are divisible by 7?",
    "subject": "mathematics",
    "class": 10,
    "year": null,
    "frequency": "high",
    "appeared_in_years": [
      2013,
      2017,
      2019,
      2022
    ],
    "chapter": "Arithmetic Progressions",
    "topic": "counting terms in an AP",
    "marks": 2,
    "type": "SA",
    "board": "CBSE",
    "answer": "Three-digit numbers divisible by 7: 105, 112, ..., 994. a = 105, d = 7, aв‚™ = 994. n = (994 в€’ 105)/7 + 1 = 889/7 + 1 = 127 + 1 = 128.",
    "source": "practice"
  },
  {
    "id": "cbse_c10_math_imp_008",
    "question": "The sum of the 4th and 8th terms of an AP is 24 and the sum of the 6th and 10th terms is 44. Find the first three terms of the AP.",
    "subject": "mathematics",
    "class": 10,
    "year": null,
    "frequency": "high",
    "appeared_in_years": [
      2015,
      2016,
      2019,
      2021
    ],
    "chapter": "Arithmetic Progressions",
    "topic": "system of equations using AP terms",
    "marks": 3,
    "type": "SA",
    "board": "CBSE",
    "answer": "aв‚„ + aв‚€ = 24 в†’ (a+3d) + (a+7d) = 24 в†’ 2a + 10d = 24 ...(i). aв‚† + aв‚Ѓв‚Ђ = 44 в†’ 2a + 14d = 44 ...(ii). Subtracting: 4d = 20 в†’ d = 5. From (i): 2a = 24 в€’ 50 = в€’26 в†’ a = в€’13. First three terms: в€’13, в€’8, в€’3.",
    "source": "practice"
  },
  {
    "id": "cbse_c10_math_imp_009",
    "question": "A sum of в‚№700 is to be used to give seven cash prizes to students of a school for their overall academic performance. If each prize is в‚№20 less than its preceding prize, find the value of each of the prizes.",
    "subject": "mathematics",
    "class": 10,
    "year": null,
    "frequency": "high",
    "appeared_in_years": [
      2012,
      2015,
      2018,
      2020
    ],
    "chapter": "Arithmetic Progressions",
    "topic": "word problems вЂ“ AP application",
    "marks": 4,
    "type": "LA",
    "board": "CBSE",
    "answer": "Prizes form an AP with d = в€’20, n = 7, Sв‚™ = 700. Sв‚™ = n/2[2a + (nв€’1)d] в†’ 700 = 7/2[2a в€’ 120] в†’ 200 = 2a в€’ 120 в†’ a = 160. Prizes: в‚№160, в‚№140, в‚№120, в‚№100, в‚№80, в‚№60, в‚№40.",
    "source": "practice"
  },
  {
    "id": "cbse_c10_math_imp_010",
    "question": "If the ratio of the sum of first n terms of two APs is (7n + 1) : (4n + 27), find the ratio of their 9th terms.",
    "subject": "mathematics",
    "class": 10,
    "year": null,
    "frequency": "high",
    "appeared_in_years": [
      2014,
      2016,
      2018,
      2022,
      2023
    ],
    "chapter": "Arithmetic Progressions",
    "topic": "ratio of sums вЂ“ standard result",
    "marks": 4,
    "type": "LA",
    "board": "CBSE",
    "answer": "Ratio of nth terms = (7(2nв€’1)+1) / (4(2nв€’1)+27). For 9th term, put n = 9: Numerator = 7(17)+1 = 120; Denominator = 4(17)+27 = 95. Ratio = 24:19.",
    "source": "practice"
  },
  {
    "id": "cbse_c10_math_imp_011",
    "question": "Prove that if a line is drawn parallel to one side of a triangle to intersect the other two sides in distinct points, the other two sides are divided in the same ratio. (Basic Proportionality Theorem / Thales' Theorem)",
    "subject": "mathematics",
    "class": 10,
    "year": null,
    "frequency": "high",
    "appeared_in_years": [
      2013,
      2015,
      2016,
      2017,
      2018,
      2019,
      2021,
      2022,
      2023
    ],
    "chapter": "Triangles",
    "topic": "proof вЂ“ Basic Proportionality Theorem (BPT)",
    "marks": 5,
    "type": "LA",
    "board": "CBSE",
    "answer": "Given: In в–іABC, DE в€Ґ BC where D is on AB and E is on AC. To prove: AD/DB = AE/EC. Construction: Draw EM вЉҐ AB and DN вЉҐ AC; join BE and CD. ar(ADE)/ar(BDE) = (ВЅ Г— AD Г— EM)/(ВЅ Г— DB Г— EM) = AD/DB. Similarly ar(ADE)/ar(CDE) = AE/EC. Since ar(BDE) = ar(CDE) (same base DE, same parallels), AD/DB = AE/EC. Hence proved.",
    "source": "practice"
  },
  {
    "id": "cbse_c10_math_imp_012",
    "question": "In в–іABC, DE в€Ґ BC. If AD = 3 cm, AB = 7 cm and EC = 3 cm, find AE.",
    "subject": "mathematics",
    "class": 10,
    "year": null,
    "frequency": "high",
    "appeared_in_years": [
      2014,
      2017,
      2019,
      2021
    ],
    "chapter": "Triangles",
    "topic": "application of BPT",
    "marks": 2,
    "type": "SA",
    "board": "CBSE",
    "answer": "By BPT: AD/DB = AE/EC. DB = AB в€’ AD = 4 cm. 3/4 = AE/3 в†’ AE = 9/4 = 2.25 cm.",
    "source": "practice"
  },
  {
    "id": "cbse_c10_math_imp_013",
    "question": "Prove that the ratio of areas of two similar triangles is equal to the square of the ratio of their corresponding sides.",
    "subject": "mathematics",
    "class": 10,
    "year": null,
    "frequency": "high",
    "appeared_in_years": [
      2013,
      2015,
      2017,
      2018,
      2019,
      2022
    ],
    "chapter": "Triangles",
    "topic": "proof вЂ“ area ratio of similar triangles",
    "marks": 5,
    "type": "LA",
    "board": "CBSE",
    "answer": "Given: в–іABC ~ в–іDEF. Draw AM вЉҐ BC and DN вЉҐ EF. ar(ABC)/ar(DEF) = (ВЅ Г— BC Г— AM)/(ВЅ Г— EF Г— DN). In в–іABM and в–іDEN: в€ B = в€ E (similar triangles) and в€ AMB = в€ DNE = 90В°, so в–іABM ~ в–іDEN в†’ AM/DN = AB/DE. ar(ABC)/ar(DEF) = (BC/EF) Г— (AM/DN) = (BC/EF) Г— (AB/DE) = (AB/DE)ВІ (since AB/DE = BC/EF for similar triangles). Hence proved.",
    "source": "practice"
  },
  {
    "id": "cbse_c10_math_imp_014",
    "question": "Prove that in a right triangle, the square of the hypotenuse is equal to the sum of the squares of the other two sides. (Pythagoras Theorem)",
    "subject": "mathematics",
    "class": 10,
    "year": null,
    "frequency": "high",
    "appeared_in_years": [
      2013,
      2014,
      2015,
      2016,
      2017,
      2018,
      2019,
      2020,
      2021,
      2022,
      2023
    ],
    "chapter": "Triangles",
    "topic": "proof вЂ“ Pythagoras Theorem",
    "marks": 5,
    "type": "LA",
    "board": "CBSE",
    "answer": "Given: в–іABC, right-angled at B. Draw BD вЉҐ AC. In в–іADB and в–іABC: в€ A is common, в€ ADB = в€ ABC = 90В° в†’ в–іADB ~ в–іABC в†’ AD/AB = AB/AC в†’ ABВІ = AD Г— AC ...(i). Similarly в–іBDC ~ в–іABC в†’ BCВІ = DC Г— AC ...(ii). Adding (i) and (ii): ABВІ + BCВІ = AC(AD + DC) = ACВІ. Hence proved.",
    "source": "practice"
  },
  {
    "id": "cbse_c10_math_imp_015",
    "question": "An aeroplane leaves an airport and flies due north at a speed of 1000 km/h. At the same time, another aeroplane leaves the same airport and flies due west at a speed of 1200 km/h. How far apart will the two aeroplanes be after 1ВЅ hours?",
    "subject": "mathematics",
    "class": 10,
    "year": null,
    "frequency": "high",
    "appeared_in_years": [
      2014,
      2016,
      2018,
      2020
    ],
    "chapter": "Triangles",
    "topic": "Pythagoras theorem application",
    "marks": 3,
    "type": "SA",
    "board": "CBSE",
    "answer": "Distance north = 1000 Г— 1.5 = 1500 km. Distance west = 1200 Г— 1.5 = 1800 km. Distance apart = в€љ(1500ВІ + 1800ВІ) = в€љ(2250000 + 3240000) = в€љ5490000 = 300в€љ61 km.",
    "source": "practice"
  },
  {
    "id": "cbse_c10_math_imp_016",
    "question": "Evaluate: (sinВІ63В° + sinВІ27В°) / (cosВІ17В° + cosВІ73В°)",
    "subject": "mathematics",
    "class": 10,
    "year": null,
    "frequency": "high",
    "appeared_in_years": [
      2016,
      2018,
      2019,
      2020,
      2022
    ],
    "chapter": "Trigonometry",
    "topic": "complementary angles вЂ“ evaluation",
    "marks": 1,
    "type": "MCQ",
    "board": "CBSE",
    "answer": "sin 63В° = cos 27В°, so sinВІ63В° + sinВІ27В° = cosВІ27В° + sinВІ27В° = 1. cos 17В° = sin 73В°, so cosВІ17В° + cosВІ73В° = sinВІ73В° + cosВІ73В° = 1. Answer = 1/1 = 1.",
    "source": "practice"
  },
  {
    "id": "cbse_c10_math_imp_017",
    "question": "Prove the identity: (sin Оё в€’ cos Оё + 1) / (sin Оё + cos Оё в€’ 1) = 1 / (sec Оё в€’ tan Оё)",
    "subject": "mathematics",
    "class": 10,
    "year": null,
    "frequency": "high",
    "appeared_in_years": [
      2015,
      2017,
      2019,
      2021,
      2023
    ],
    "chapter": "Trigonometry",
    "topic": "trigonometric identity proof",
    "marks": 4,
    "type": "LA",
    "board": "CBSE",
    "answer": "Divide numerator and denominator by cos Оё: LHS = (tan Оё в€’ 1 + sec Оё) / (tan Оё + 1 в€’ sec Оё). Multiply numerator and denominator by (sec Оё + tan Оё): After simplification using secВІОё в€’ tanВІОё = 1, LHS = (sec Оё + tan Оё в€’ 1) / (secВІОё в€’ tanВІОё в€’ (sec Оё в€’ tan Оё)) = ... = 1/(sec Оё в€’ tan Оё) = RHS. Hence proved.",
    "source": "practice"
  },
  {
    "id": "cbse_c10_math_imp_018",
    "question": "If tan Оё + sin Оё = m and tan Оё в€’ sin Оё = n, show that mВІ в€’ nВІ = 4в€љ(mn).",
    "subject": "mathematics",
    "class": 10,
    "year": null,
    "frequency": "high",
    "appeared_in_years": [
      2017,
      2019,
      2021,
      2023
    ],
    "chapter": "Trigonometry",
    "topic": "trigonometric identity proof",
    "marks": 4,
    "type": "LA",
    "board": "CBSE",
    "answer": "mВІ в€’ nВІ = (m+n)(mв€’n) = (2 tan Оё)(2 sin Оё) = 4 tan Оё sin Оё. mn = (tan Оё + sin Оё)(tan Оё в€’ sin Оё) = tanВІОё в€’ sinВІОё = sinВІОё/cosВІОё в€’ sinВІОё = sinВІОё(1в€’cosВІОё)/cosВІОё = sinВІОё tanВІОё. So 4в€љ(mn) = 4в€љ(sinВІОё tanВІОё) = 4 sin Оё tan Оё. Hence mВІ в€’ nВІ = 4в€љ(mn).",
    "source": "practice"
  },
  {
    "id": "cbse_c10_math_imp_019",
    "question": "Prove that: (cosec A в€’ sin A)(sec A в€’ cos A) = 1/(tan A + cot A)",
    "subject": "mathematics",
    "class": 10,
    "year": null,
    "frequency": "high",
    "appeared_in_years": [
      2014,
      2016,
      2018,
      2022
    ],
    "chapter": "Trigonometry",
    "topic": "trigonometric identity proof",
    "marks": 3,
    "type": "SA",
    "board": "CBSE",
    "answer": "LHS = (cosВІA/sin A)(sinВІA/cos A) = sin A cos A. RHS = 1/(sin A/cos A + cos A/sin A) = sin A cos A/(sinВІA + cosВІA) = sin A cos A. LHS = RHS. Hence proved.",
    "source": "practice"
  },
  {
    "id": "cbse_c10_math_imp_020",
    "question": "The angle of elevation of the top of a building from the foot of a tower is 30В° and the angle of elevation of the top of the tower from the foot of the building is 45В°. If the tower is 30 m high, find the height of the building.",
    "subject": "mathematics",
    "class": 10,
    "year": null,
    "frequency": "high",
    "appeared_in_years": [
      2013,
      2015,
      2016,
      2017,
      2019,
      2022
    ],
    "chapter": "Trigonometry",
    "topic": "heights and distances",
    "marks": 4,
    "type": "LA",
    "board": "CBSE",
    "answer": "Let height of building = h, horizontal distance = d. tan 45В° = 30/d в†’ d = 30 m. tan 30В° = h/d в†’ h = 30/в€љ3 = 10в€љ3 m в‰€ 17.32 m.",
    "source": "practice"
  },
  {
    "id": "cbse_c10_math_imp_021",
    "question": "From the top of a 60 m high building, the angles of depression of the top and bottom of a tower are 45В° and 60В° respectively. Find the height of the tower and the horizontal distance between the building and tower.",
    "subject": "mathematics",
    "class": 10,
    "year": null,
    "frequency": "high",
    "appeared_in_years": [
      2014,
      2016,
      2018,
      2019,
      2023
    ],
    "chapter": "Trigonometry",
    "topic": "heights and distances вЂ“ two angles",
    "marks": 5,
    "type": "LA",
    "board": "CBSE",
    "answer": "Let building AB = 60 m, tower CD = h, horizontal distance = d. tan 60В° = 60/d в†’ d = 60/в€љ3 = 20в€љ3 m. tan 45В° = (60в€’h)/d в†’ 1 = (60в€’h)/(20в€љ3) в†’ 60в€’h = 20в€љ3 в†’ h = 60 в€’ 20в€љ3 = 20(3в€’в€љ3) m. Horizontal distance = 20в€љ3 m в‰€ 34.64 m.",
    "source": "practice"
  },
  {
    "id": "cbse_c10_math_imp_022",
    "question": "An observer 1.5 m tall is 28.5 m away from a chimney. The angle of elevation of the top of the chimney from his eyes is 45В°. What is the height of the chimney?",
    "subject": "mathematics",
    "class": 10,
    "year": null,
    "frequency": "high",
    "appeared_in_years": [
      2013,
      2018,
      2020,
      2022
    ],
    "chapter": "Trigonometry",
    "topic": "heights and distances вЂ“ observer height",
    "marks": 3,
    "type": "SA",
    "board": "CBSE",
    "answer": "Let height of chimney = h. Eye level = 1.5 m above ground. tan 45В° = (h в€’ 1.5)/28.5 в†’ 1 = (h в€’ 1.5)/28.5 в†’ h = 30 m.",
    "source": "practice"
  },
  {
    "id": "cbse_c10_math_imp_023",
    "question": "Find the area of the shaded region where ABCD is a square of side 14 cm and four circles of radius 3.5 cm are drawn inside the square, each touching two adjacent sides. [Use ПЂ = 22/7]",
    "subject": "mathematics",
    "class": 10,
    "year": null,
    "frequency": "high",
    "appeared_in_years": [
      2015,
      2017,
      2019,
      2021,
      2023
    ],
    "chapter": "Areas Related to Circles",
    "topic": "area of shaded region вЂ“ squares and circles",
    "marks": 4,
    "type": "LA",
    "board": "CBSE",
    "answer": "Area of square = 14ВІ = 196 cmВІ. Area of 4 circles = 4 Г— ПЂ Г— 3.5ВІ = 4 Г— (22/7) Г— 12.25 = 154 cmВІ. Shaded area = 196 в€’ 154 = 42 cmВІ.",
    "source": "practice"
  },
  {
    "id": "cbse_c10_math_imp_024",
    "question": "In a circle of radius 21 cm, an arc subtends an angle of 60В° at the centre. Find: (i) the length of the arc, (ii) the area of the sector formed, (iii) the area of the segment formed. [Use ПЂ = 22/7 and в€љ3 = 1.732]",
    "subject": "mathematics",
    "class": 10,
    "year": null,
    "frequency": "high",
    "appeared_in_years": [
      2014,
      2016,
      2017,
      2018,
      2020,
      2022
    ],
    "chapter": "Areas Related to Circles",
    "topic": "arc length, sector area, segment area",
    "marks": 4,
    "type": "LA",
    "board": "CBSE",
    "answer": "(i) Arc length = (Оё/360) Г— 2ПЂr = (60/360) Г— 2 Г— (22/7) Г— 21 = 22 cm. (ii) Area of sector = (Оё/360) Г— ПЂrВІ = (60/360) Г— (22/7) Г— 441 = 231 cmВІ. (iii) The chord for a 60В° arc in a circle of radius 21 cm forms an equilateral triangle (since OA = OB = 21 and в€ AOB = 60В°, triangle OAB is equilateral with side 21 cm). Area of equilateral triangle OAB = (в€љ3/4) Г— 21ВІ = (в€љ3/4) Г— 441 = 441в€љ3/4. Using в€љ3 = 1.732: = 441 Г— 1.732/4 = 763.812/4 = 190.953 cmВІ. Area of segment = 231 в€’ 190.953 в‰€ 40.05 cmВІ.",
    "source": "practice"
  },
  {
    "id": "cbse_c10_math_imp_025",
    "question": "A horse is tied to a peg at one corner of a square shaped grass field of side 15 m by means of a 5 m long rope. Find: (i) the area of that part of the field in which the horse can graze, (ii) the increase in the grazing area if the rope were 10 m long instead of 5 m. [Use ПЂ = 3.14]",
    "subject": "mathematics",
    "class": 10,
    "year": null,
    "frequency": "high",
    "appeared_in_years": [
      2012,
      2015,
      2019,
      2021
    ],
    "chapter": "Areas Related to Circles",
    "topic": "sector area вЂ“ quadrant application",
    "marks": 4,
    "type": "LA",
    "board": "CBSE",
    "answer": "(i) Area = (90/360) Г— ПЂ Г— 5ВІ = (1/4) Г— 3.14 Г— 25 = 19.625 mВІ. (ii) Area with 10 m rope = (1/4) Г— 3.14 Г— 100 = 78.5 mВІ. Increase = 78.5 в€’ 19.625 = 58.875 mВІ.",
    "source": "practice"
  },
  {
    "id": "cbse_c10_math_imp_026",
    "question": "A gulab jamun, when ready for eating, contains sugar syrup of about 30% of its volume. Find approximately how much syrup would be found in 45 gulab jamuns, each shaped like a cylinder with two hemispherical ends with the total length 5 cm and diameter 2.8 cm. [Use ПЂ = 22/7]",
    "subject": "mathematics",
    "class": 10,
    "year": null,
    "frequency": "high",
    "appeared_in_years": [
      2014,
      2016,
      2018,
      2020
    ],
    "chapter": "Surface Areas and Volumes",
    "topic": "volume of combined solids вЂ“ cylinder + hemispheres",
    "marks": 4,
    "type": "LA",
    "board": "CBSE",
    "answer": "Radius = 1.4 cm. Length of cylindrical part = 5 в€’ 2Г—1.4 = 2.2 cm. Volume of one gulab jamun = ПЂ(1.4)ВІ(2.2) + (4/3)ПЂ(1.4)Ві = (22/7)[1.96Г—2.2 + (4/3)Г—2.744] = (22/7)[4.312 + 3.658] = (22/7) Г— 7.97 в‰€ 25.05 cmВі. Total volume of 45 = 45 Г— 25.05 в‰€ 1127.25 cmВі. Syrup = 30% of 1127.25 в‰€ 338.2 cmВі.",
    "source": "practice"
  },
  {
    "id": "cbse_c10_math_imp_027",
    "question": "A solid iron pole consists of a cylinder of height 220 cm and base diameter 24 cm, which is surmounted by another cylinder of height 60 cm and radius 8 cm. Find the mass of the pole, given that 1 cmВі of iron has approximately 8 g mass. [Use ПЂ = 3.14]",
    "subject": "mathematics",
    "class": 10,
    "year": null,
    "frequency": "high",
    "appeared_in_years": [
      2015,
      2017,
      2019,
      2022
    ],
    "chapter": "Surface Areas and Volumes",
    "topic": "volume of combined cylinders",
    "marks": 4,
    "type": "LA",
    "board": "CBSE",
    "answer": "Volume of larger cylinder = ПЂ(12)ВІ(220) = 3.14 Г— 144 Г— 220 = 99475.2 cmВі. Volume of smaller cylinder = 3.14 Г— 64 Г— 60 = 12057.6 cmВі. Total volume = 111532.8 cmВі. Mass = 111532.8 Г— 8 = 892262.4 g в‰€ 892.26 kg.",
    "source": "practice"
  },
  {
    "id": "cbse_c10_math_imp_028",
    "question": "A hemispherical tank is made up of an iron sheet 1 cm thick. If the inner radius is 1 m, then find the volume of the iron used to make the tank. [Use ПЂ = 22/7]",
    "subject": "mathematics",
    "class": 10,
    "year": null,
    "frequency": "high",
    "appeared_in_years": [
      2013,
      2016,
      2019,
      2021
    ],
    "chapter": "Surface Areas and Volumes",
    "topic": "volume of hollow hemisphere",
    "marks": 3,
    "type": "SA",
    "board": "CBSE",
    "answer": "Inner radius r = 1 m = 100 cm, outer radius R = 101 cm. Volume = (2/3)ПЂ(RВі в€’ rВі) = (2/3) Г— (22/7) Г— (101Ві в€’ 100Ві). 101Ві в€’ 100Ві = (101в€’100)(101ВІ + 101Г—100 + 100ВІ) = 30301. Volume = (2/3) Г— (22/7) Г— 30301 в‰€ 63487 cmВі в‰€ 0.06349 mВі.",
    "source": "practice"
  },
  {
    "id": "cbse_c10_math_imp_029",
    "question": "Water in a canal, 6 m wide and 1.5 m deep, is flowing with a speed of 10 km/h. How much area will it irrigate in 30 minutes, if 8 cm of standing water is needed?",
    "subject": "mathematics",
    "class": 10,
    "year": null,
    "frequency": "high",
    "appeared_in_years": [
      2015,
      2017,
      2020,
      2022,
      2023
    ],
    "chapter": "Surface Areas and Volumes",
    "topic": "volume conversion вЂ“ canal and irrigation",
    "marks": 4,
    "type": "LA",
    "board": "CBSE",
    "answer": "Length of water flowing in 30 min = (10 Г— 1000)/2 = 5000 m. Volume of water = 6 Г— 1.5 Г— 5000 = 45000 mВі. Area irrigated = 45000 / 0.08 = 562500 mВІ.",
    "source": "practice"
  },
  {
    "id": "cbse_c10_math_imp_030",
    "question": "The following frequency distribution gives the monthly consumption of electricity of 68 consumers of a locality. Find the median, mean and mode of the data and compare them.\n\nMonthly consumption (units): 65вЂ“85, 85вЂ“105, 105вЂ“125, 125вЂ“145, 145вЂ“165, 165вЂ“185, 185вЂ“205\nNo. of consumers: 4, 5, 13, 20, 14, 8, 4",
    "subject": "mathematics",
    "class": 10,
    "year": null,
    "frequency": "high",
    "appeared_in_years": [
      2012,
      2015,
      2018,
      2020,
      2022
    ],
    "chapter": "Statistics",
    "topic": "mean, median, mode вЂ“ grouped data",
    "marks": 5,
    "type": "LA",
    "board": "CBSE",
    "answer": "Median: n=68, n/2=34. cf values: 4,9,22,42. Median class: 125вЂ“145. Median = 125 + [(34в€’22)/20] Г— 20 = 125 + 12 = 137 units. Mode: Max frequency = 20, modal class = 125вЂ“145. Mode = 125 + [(20в€’13)/(2Г—20в€’13в€’14)] Г— 20 = 125 + (7/13) Г— 20 в‰€ 135.77 units. Mean using assumed mean (a=135, h=20): step deviations give ОЈfГ—u = 7, mean = 135 + (7/68) Г— 20 в‰€ 137.06 units.",
    "source": "practice"
  },
  {
    "id": "cbse_c10_math_imp_031",
    "question": "If the mean of the following distribution is 27, find the value of p:\n\nClass: 0вЂ“10, 10вЂ“20, 20вЂ“30, 30вЂ“40, 40вЂ“50\nFrequency: 8, p, 12, 13, 10",
    "subject": "mathematics",
    "class": 10,
    "year": null,
    "frequency": "high",
    "appeared_in_years": [
      2014,
      2016,
      2019,
      2021,
      2023
    ],
    "chapter": "Statistics",
    "topic": "finding missing frequency using mean",
    "marks": 3,
    "type": "SA",
    "board": "CBSE",
    "answer": "ОЈf = 43 + p. ОЈfx = 8Г—5 + pГ—15 + 12Г—25 + 13Г—35 + 10Г—45 = 40 + 15p + 300 + 455 + 450 = 1245 + 15p. Mean = (1245 + 15p)/(43 + p) = 27 в†’ 1245 + 15p = 27(43 + p) в†’ 1245 + 15p = 1161 + 27p в†’ 84 = 12p в†’ p = 7.",
    "source": "practice"
  },
  {
    "id": "cbse_c10_math_imp_032",
    "question": "The following table gives production yield per hectare of wheat of 100 farms of a village. Change the distribution to a 'more than' type distribution and draw its ogive.\n\nProduction yield (kg/ha): 50вЂ“55, 55вЂ“60, 60вЂ“65, 65вЂ“70, 70вЂ“75, 75вЂ“80\nNo. of farms: 2, 8, 12, 24, 38, 16",
    "subject": "mathematics",
    "class": 10,
    "year": null,
    "frequency": "high",
    "appeared_in_years": [
      2013,
      2016,
      2018,
      2020,
      2022
    ],
    "chapter": "Statistics",
    "topic": "ogive вЂ“ more than type",
    "marks": 4,
    "type": "LA",
    "board": "CBSE",
    "answer": "More than type: more than 50: 100, more than 55: 98, more than 60: 90, more than 65: 78, more than 70: 54, more than 75: 16. Plot points (50,100), (55,98), (60,90), (65,78), (70,54), (75,16) and join with smooth curve. The ogive is a downward sloping curve.",
    "source": "practice"
  },
  {
    "id": "cbse_c10_math_imp_033",
    "question": "The median of the following data is 525. Find the values of x and y, if total frequency is 100.\n\nClass: 0вЂ“100, 100вЂ“200, 200вЂ“300, 300вЂ“400, 400вЂ“500, 500вЂ“600, 600вЂ“700, 700вЂ“800, 800вЂ“900, 900вЂ“1000\nFrequency: 2, 5, x, 12, 17, 20, y, 9, 7, 4",
    "subject": "mathematics",
    "class": 10,
    "year": null,
    "frequency": "high",
    "appeared_in_years": [
      2015,
      2017,
      2019,
      2021,
      2023
    ],
    "chapter": "Statistics",
    "topic": "finding missing frequencies using median",
    "marks": 5,
    "type": "LA",
    "board": "CBSE",
    "answer": "ОЈf = 76 + x + y = 100 в†’ x + y = 24 ...(i). Median = 525, so median class = 500вЂ“600. cf before 500вЂ“600 = 2+5+x+12+17 = 36+x. Median = l + [(n/2 в€’ cf)/f] Г— h в†’ 525 = 500 + [(50 в€’ 36 в€’ x)/20] Г— 100 в†’ 25 = 5(14 в€’ x) в†’ 5 = 14 в€’ x в†’ x = 9. From (i): y = 15.",
    "source": "practice"
  },
  {
    "id": "cbse_c10_math_imp_034",
    "question": "A card is drawn at random from a well-shuffled deck of 52 playing cards. Find the probability that the card drawn is: (i) a king or queen, (ii) a non-ace, (iii) a black face card.",
    "subject": "mathematics",
    "class": 10,
    "year": null,
    "frequency": "high",
    "appeared_in_years": [
      2013,
      2015,
      2017,
      2019,
      2021,
      2022
    ],
    "chapter": "Probability",
    "topic": "cards вЂ“ combined events",
    "marks": 3,
    "type": "SA",
    "board": "CBSE",
    "answer": "(i) P(king or queen) = (4+4)/52 = 8/52 = 2/13. (ii) P(non-ace) = (52в€’4)/52 = 48/52 = 12/13. (iii) Black face cards = 6 (J, Q, K of spades and clubs). P = 6/52 = 3/26.",
    "source": "practice"
  },
  {
    "id": "cbse_c10_math_imp_035",
    "question": "Two dice are thrown at the same time. Find the probability that the sum of the two numbers appearing on the top of the dice is: (i) 8, (ii) 13, (iii) less than or equal to 12.",
    "subject": "mathematics",
    "class": 10,
    "year": null,
    "frequency": "high",
    "appeared_in_years": [
      2014,
      2016,
      2018,
      2020,
      2022
    ],
    "chapter": "Probability",
    "topic": "two dice вЂ“ sum problems",
    "marks": 3,
    "type": "SA",
    "board": "CBSE",
    "answer": "Total outcomes = 36. (i) Sum=8: (2,6),(3,5),(4,4),(5,3),(6,2) = 5 outcomes. P = 5/36. (ii) Sum=13: impossible with two dice. P = 0. (iii) Sum в‰¤ 12: all 36 outcomes qualify. P = 36/36 = 1.",
    "source": "practice"
  },
  {
    "id": "cbse_c10_math_imp_036",
    "question": "A bag contains 5 red balls and some blue balls. If the probability of drawing a blue ball is double that of a red ball, find the number of blue balls in the bag.",
    "subject": "mathematics",
    "class": 10,
    "year": null,
    "frequency": "high",
    "appeared_in_years": [
      2012,
      2015,
      2017,
      2019,
      2021
    ],
    "chapter": "Probability",
    "topic": "setting up probability equations",
    "marks": 2,
    "type": "SA",
    "board": "CBSE",
    "answer": "Let number of blue balls = x. P(red) = 5/(5+x), P(blue) = x/(5+x). Given: x/(5+x) = 2 Г— 5/(5+x) в†’ x = 10. Number of blue balls = 10.",
    "source": "practice"
  },
  {
    "id": "cbse_c10_math_imp_037",
    "question": "A game consists of tossing a coin 3 times and noting its outcome each time. Hanif wins if all the tosses give the same result i.e., three heads or three tails, and loses otherwise. Calculate the probability that Hanif will lose the game.",
    "subject": "mathematics",
    "class": 10,
    "year": null,
    "frequency": "high",
    "appeared_in_years": [
      2013,
      2016,
      2018,
      2020
    ],
    "chapter": "Probability",
    "topic": "coins вЂ“ complementary events",
    "marks": 2,
    "type": "SA",
    "board": "CBSE",
    "answer": "Total outcomes = 8 (HHH, HHT, HTH, THH, HTT, THT, TTH, TTT). Winning outcomes = {HHH, TTT} = 2. P(win) = 2/8 = 1/4. P(lose) = 1 в€’ 1/4 = 3/4.",
    "source": "practice"
  },
  {
    "id": "cbse_c10_math_imp_038",
    "question": "100 surnames were randomly picked up from a local telephone directory and the frequency distribution of the number of letters in English alphabets in the surnames was obtained as follows:\n\nNo. of letters: 1вЂ“4, 4вЂ“7, 7вЂ“10, 10вЂ“13, 13вЂ“16, 16вЂ“19\nNo. of surnames: 6, 30, 40, 16, 4, 4\n\nDetermine the median and mean number of letters in the surnames. Also find the modal size.",
    "subject": "mathematics",
    "class": 10,
    "year": null,
    "frequency": "high",
    "appeared_in_years": [
      2014,
      2018,
      2020,
      2023
    ],
    "chapter": "Statistics",
    "topic": "mean, median, mode вЂ“ combined",
    "marks": 5,
    "type": "LA",
    "board": "CBSE",
    "answer": "Median: n/2=50. cf: 6, 36, 76. Median class: 7вЂ“10. Median = 7 + [(50в€’36)/40] Г— 3 = 7 + 1.05 = 8.05. Mode: max f=40, modal class = 7вЂ“10. Mode = 7 + [(40в€’30)/(80в€’30в€’16)] Г— 3 = 7 + (10/34) Г— 3 в‰€ 7.88. Mean = [6Г—2.5 + 30Г—5.5 + 40Г—8.5 + 16Г—11.5 + 4Г—14.5 + 4Г—17.5]/100 = [15+165+340+184+58+70]/100 = 832/100 = 8.32.",
    "source": "practice"
  },
  {
    "id": "cbse_c10_math_imp_039",
    "question": "A chord of a circle of radius 10 cm subtends a right angle at the centre. Find the area of the corresponding: (i) minor segment, (ii) major sector. [Use ПЂ = 3.14]",
    "subject": "mathematics",
    "class": 10,
    "year": null,
    "frequency": "high",
    "appeared_in_years": [
      2016,
      2018,
      2019,
      2021,
      2022
    ],
    "chapter": "Areas Related to Circles",
    "topic": "minor segment and major sector",
    "marks": 4,
    "type": "LA",
    "board": "CBSE",
    "answer": "(i) Area of minor sector = (90/360) Г— 3.14 Г— 100 = 78.5 cmВІ. Area of right triangle = ВЅ Г— 10 Г— 10 = 50 cmВІ. Area of minor segment = 78.5 в€’ 50 = 28.5 cmВІ. (ii) Area of major sector = (270/360) Г— 3.14 Г— 100 = 235.5 cmВІ.",
    "source": "practice"
  },
  {
    "id": "cbse_c10_math_imp_040",
    "question": "From the top of a tower 100 m high, a man observes two cars on the opposite sides of the tower with angles of depression 30В° and 45В° respectively. Find the distance between the cars. [Use в€љ3 = 1.73]",
    "subject": "mathematics",
    "class": 10,
    "year": null,
    "frequency": "high",
    "appeared_in_years": [
      2015,
      2017,
      2018,
      2020,
      2023
    ],
    "chapter": "Trigonometry",
    "topic": "heights and distances вЂ“ opposite sides",
    "marks": 4,
    "type": "LA",
    "board": "CBSE",
    "answer": "Height of tower AB = 100 m. For car at 30В°: tan 30В° = 100/dв‚Ѓ в†’ dв‚Ѓ = 100в€љ3 m. For car at 45В°: tan 45В° = 100/dв‚‚ в†’ dв‚‚ = 100 m. Distance between cars = dв‚Ѓ + dв‚‚ = 100в€љ3 + 100 = 100(в€љ3 + 1) = 100 Г— 2.73 = 273 m.",
    "source": "practice"
  }
]