[
  {
    "id": "cbse_c10_math_num_001",
    "question": "The angle of elevation of the top of a building from a point on the ground, which is 30 m away from the foot of the building, is 30°. Find the height of the building.",
    "subject": "mathematics",
    "class": 10,
    "year": null,
    "chapter": "Some Applications of Trigonometry",
    "topic": "heights and distances",
    "marks": 3,
    "type": "SA",
    "board": "CBSE",
    "answer": "Let height = h. tan 30° = h/30. h = 30 × (1/√3) = 30/√3 = 10√3 m ≈ 17.32 m",
    "source": "practice"
  },
  {
    "id": "cbse_c10_math_num_002",
    "question": "A ladder 15 m long just reaches the top of a vertical wall. If the ladder makes an angle of 60° with the wall, find the height of the wall.",
    "subject": "mathematics",
    "class": 10,
    "year": null,
    "chapter": "Some Applications of Trigonometry",
    "topic": "heights and distances",
    "marks": 2,
    "type": "SA",
    "board": "CBSE",
    "answer": "The ladder makes 60° with wall, so 30° with horizontal. cos 60° = h/15 → h = 15 × cos 60° = 15 × (1/2) = 7.5 m",
    "source": "practice"
  },
  {
    "id": "cbse_c10_math_num_003",
    "question": "A tower is 20 m high and casts a shadow of 20√3 m on the ground. Find the angle of elevation of the sun.",
    "subject": "mathematics",
    "class": 10,
    "year": null,
    "chapter": "Some Applications of Trigonometry",
    "topic": "heights and distances",
    "marks": 1,
    "type": "VSA",
    "board": "CBSE",
    "answer": "tan θ = height/shadow = 20/(20√3) = 1/√3. Therefore θ = tan⁻¹(1/√3) = 30°",
    "source": "practice"
  },
  {
    "id": "cbse_c10_math_num_004",
    "question": "A tower 30 m high casts a shadow 10√3 m long on the ground. Find the angle of elevation of the sun.",
    "subject": "mathematics",
    "class": 10,
    "year": null,
    "chapter": "Some Applications of Trigonometry",
    "topic": "heights and distances",
    "marks": 1,
    "type": "VSA",
    "board": "CBSE",
    "answer": "tan θ = 30/(10√3) = 3/√3 = √3. Therefore θ = 60°",
    "source": "practice"
  },
  {
    "id": "cbse_c10_math_num_005",
    "question": "The angle of elevation of the top of a vertical tower from a point on the ground is 60°. From another point 10 m vertically above the first, the angle of elevation of the top of the tower is 30°. Find the height of the tower.",
    "subject": "mathematics",
    "class": 10,
    "year": null,
    "chapter": "Some Applications of Trigonometry",
    "topic": "heights and distances",
    "marks": 4,
    "type": "LA",
    "board": "CBSE",
    "answer": "Let tower height = H, horizontal distance = d. From ground: tan 60° = H/d → d = H/√3. From 10 m height: tan 30° = (H-10)/d → (H-10)/d = 1/√3. Substituting: (H-10)/(H/√3) = 1/√3 → √3(H-10) = H/√3 → 3(H-10) = H → 3H - 30 = H → H = 15 m",
    "source": "practice"
  },
  {
    "id": "cbse_c10_math_num_006",
    "question": "From the top of a 100 m high tower, the angles of depression of two cars on the opposite sides are 30° and 45°. Find the distance between the two cars.",
    "subject": "mathematics",
    "class": 10,
    "year": null,
    "chapter": "Some Applications of Trigonometry",
    "topic": "heights and distances",
    "marks": 4,
    "type": "LA",
    "board": "CBSE",
    "answer": "For car 1 (angle 45°): tan 45° = 100/d₁ → d₁ = 100 m. For car 2 (angle 30°): tan 30° = 100/d₂ → d₂ = 100√3 m. Distance between cars = d₁ + d₂ = 100 + 100√3 = 100(1 + √3) ≈ 273.2 m",
    "source": "practice"
  },
  {
    "id": "cbse_c10_math_num_007",
    "question": "An observer 1.5 m tall is 28.5 m away from a tower of height 30 m. Find the angle of elevation of the top of the tower from the eye of the observer.",
    "subject": "mathematics",
    "class": 10,
    "year": null,
    "chapter": "Some Applications of Trigonometry",
    "topic": "heights and distances",
    "marks": 2,
    "type": "SA",
    "board": "CBSE",
    "answer": "Effective height = tower height - observer height = 30 - 1.5 = 28.5 m. Horizontal distance = 28.5 m. tan θ = 28.5/28.5 = 1 = tan 45°. Therefore angle of elevation = 45°",
    "source": "practice"
  },
  {
    "id": "cbse_c10_math_num_008",
    "question": "The tops of two poles of heights 16 m and 12 m are connected by a wire. The wire makes an angle of 30° with the horizontal. Find the length of the wire.",
    "subject": "mathematics",
    "class": 10,
    "year": null,
    "chapter": "Some Applications of Trigonometry",
    "topic": "heights and distances",
    "marks": 2,
    "type": "SA",
    "board": "CBSE",
    "answer": "Height difference = 16 - 12 = 4 m. Wire makes 30° with horizontal, so sin 30° = 4/L → 1/2 = 4/L → L = 8 m",
    "source": "practice"
  },
  {
    "id": "cbse_c10_math_num_009",
    "question": "From the top of a 25 m high cliff, the angle of elevation of a tower is equal to the angle of depression of the foot of the tower. Find the height of the tower.",
    "subject": "mathematics",
    "class": 10,
    "year": null,
    "chapter": "Some Applications of Trigonometry",
    "topic": "heights and distances",
    "marks": 3,
    "type": "SA",
    "board": "CBSE",
    "answer": "Let angle = θ. Let horizontal distance = d, extra tower height above cliff = y. tan θ = y/d (elevation) and tan θ = 25/d (depression). Therefore y = 25 m. Total tower height = 25 + 25 = 50 m",
    "source": "practice"
  },
  {
    "id": "cbse_c10_math_num_010",
    "question": "AB is a 6 m high pole and CD is a ladder inclined at 60° to the horizontal, reaching point D on the pole. If AD = 2.54 m, find the length of the ladder. (Use √3 = 1.73)",
    "subject": "mathematics",
    "class": 10,
    "year": null,
    "chapter": "Some Applications of Trigonometry",
    "topic": "heights and distances",
    "marks": 3,
    "type": "SA",
    "board": "CBSE",
    "answer": "DB = AB - AD = 6 - 2.54 = 3.46 m. sin 60° = DB/CD → (√3/2) = 3.46/CD → CD = 3.46 × 2/1.73 = 4 m",
    "source": "practice"
  },
  {
    "id": "cbse_c10_math_num_011",
    "question": "Find the area of a sector of a circle with radius 14 cm and central angle 60°. (Use π = 22/7)",
    "subject": "mathematics",
    "class": 10,
    "year": null,
    "chapter": "Areas Related to Circles",
    "topic": "sector area",
    "marks": 2,
    "type": "SA",
    "board": "CBSE",
    "answer": "Area of sector = (θ/360°) × πr² = (60/360) × (22/7) × 14² = (1/6) × (22/7) × 196 = (1/6) × 616 = 102.67 cm²",
    "source": "practice"
  },
  {
    "id": "cbse_c10_math_num_012",
    "question": "A circle has radius 21 cm. Find the area of the sector with central angle 60°. (Use π = 22/7)",
    "subject": "mathematics",
    "class": 10,
    "year": null,
    "chapter": "Areas Related to Circles",
    "topic": "sector area",
    "marks": 2,
    "type": "SA",
    "board": "CBSE",
    "answer": "Area = (θ/360°) × πr² = (60/360) × (22/7) × 21² = (1/6) × (22/7) × 441 = (1/6) × 1386 = 231 cm²",
    "source": "practice"
  },
  {
    "id": "cbse_c10_math_num_013",
    "question": "Find the area of the minor segment of a circle of radius 14 cm, with central angle 60°. Also find the area of the major segment. (Use π = 22/7 and √3 = 1.73)",
    "subject": "mathematics",
    "class": 10,
    "year": null,
    "chapter": "Areas Related to Circles",
    "topic": "segment area",
    "marks": 3,
    "type": "SA",
    "board": "CBSE",
    "answer": "Area of sector = (60/360) × (22/7) × 196 = 102.67 cm². Area of triangle = (√3/4) × 14² = (1.73/4) × 196 = 84.77 cm². Area of minor segment = 102.67 - 84.77 = 17.9 cm². Area of major segment = π × 196 - 17.9 = 616 - 17.9 = 598.1 cm²",
    "source": "practice"
  },
  {
    "id": "cbse_c10_math_num_014",
    "question": "A chord of a circle of radius 35 cm subtends a right angle at the centre. Find the area of the major segment. (Use π = 22/7)",
    "subject": "mathematics",
    "class": 10,
    "year": null,
    "chapter": "Areas Related to Circles",
    "topic": "segment area",
    "marks": 3,
    "type": "SA",
    "board": "CBSE",
    "answer": "Area of minor sector = (90/360) × (22/7) × 35² = (1/4) × (22/7) × 1225 = 962.5 cm². Area of triangle = (1/2) × 35 × 35 = 612.5 cm². Area of minor segment = 962.5 - 612.5 = 350 cm². Area of circle = (22/7) × 1225 = 3850 cm². Area of major segment = 3850 - 350 = 3500 cm²",
    "source": "practice"
  },
  {
    "id": "cbse_c10_math_num_015",
    "question": "Two concentric circles have radii 21 cm and 42 cm. If ∠AOB = 60°, find the area of the shaded region between the two arcs. (Use π = 22/7)",
    "subject": "mathematics",
    "class": 10,
    "year": null,
    "chapter": "Areas Related to Circles",
    "topic": "sector area",
    "marks": 3,
    "type": "SA",
    "board": "CBSE",
    "answer": "Area of larger sector = (60/360) × (22/7) × 42² = (1/6) × (22/7) × 1764 = 924 cm². Area of smaller sector = (60/360) × (22/7) × 21² = (1/6) × (22/7) × 441 = 231 cm². Shaded area = 924 - 231 = 693 cm²",
    "source": "practice"
  },
  {
    "id": "cbse_c10_math_num_016",
    "question": "A square OABC is inscribed in a quadrant OPBQ of a circle. If OA = 20 cm, find the area of the shaded region between the quadrant and the square. (Use π = 3.14)",
    "subject": "mathematics",
    "class": 10,
    "year": null,
    "chapter": "Areas Related to Circles",
    "topic": "combined figures",
    "marks": 3,
    "type": "SA",
    "board": "CBSE",
    "answer": "Side of square = 20 cm. Diagonal of square = radius of quadrant = 20√2 cm. Area of quadrant = (1/4) × π × (20√2)² = (1/4) × 3.14 × 800 = 628 cm². Area of square = 20² = 400 cm². Shaded area = 628 - 400 = 228 cm²",
    "source": "practice"
  },
  {
    "id": "cbse_c10_math_num_017",
    "question": "In a right triangle with legs AB = 3 cm and AC = 4 cm (hypotenuse BC = 5 cm), semicircles are drawn on each side. Find the area of the shaded region (Hippocrates lune).",
    "subject": "mathematics",
    "class": 10,
    "year": null,
    "chapter": "Areas Related to Circles",
    "topic": "combined figures",
    "marks": 4,
    "type": "LA",
    "board": "CBSE",
    "answer": "Sum of areas of semicircles on AB and AC = (1/2)π(1.5²) + (1/2)π(2²) = (1/2)π(2.25 + 4) = (1/2) × π × 6.25. Area of semicircle on BC = (1/2)π(2.5²) = (1/2) × π × 6.25. By Pythagoras, these are equal. Area of triangle = (1/2) × 3 × 4 = 6 cm². Shaded area = 6 cm²",
    "source": "practice"
  },
  {
    "id": "cbse_c10_math_num_018",
    "question": "A cone of height 24 cm and slant height 25 cm is mounted on a hemisphere of radius 7 cm (common base). Find the total surface area of the solid. (Use π = 22/7)",
    "subject": "mathematics",
    "class": 10,
    "year": null,
    "chapter": "Surface Areas and Volumes",
    "topic": "combined solid TSA",
    "marks": 4,
    "type": "LA",
    "board": "CBSE",
    "answer": "Radius r = 7 cm, cone slant height l = 25 cm. TSA = Curved SA of cone + Curved SA of hemisphere = πrl + 2πr² = πr(l + 2r) = (22/7) × 7 × (25 + 14) = 22 × 39 = 858 cm²",
    "source": "practice"
  },
  {
    "id": "cbse_c10_math_num_019",
    "question": "A sphere of diameter 18 cm is dropped into a cylindrical vessel of diameter 36 cm, partly filled with water. If the sphere is completely submerged, find the rise in water level.",
    "subject": "mathematics",
    "class": 10,
    "year": null,
    "chapter": "Surface Areas and Volumes",
    "topic": "volume displacement",
    "marks": 3,
    "type": "SA",
    "board": "CBSE",
    "answer": "Sphere radius = 9 cm. Cylinder radius = 18 cm. Volume of sphere = (4/3)π × 9³ = 972π cm³. Rise in level × πR² = Volume of sphere → h × π × 324 = 972π → h = 972/324 = 3 cm",
    "source": "practice"
  },
  {
    "id": "cbse_c10_math_num_020",
    "question": "Find the number of solid spheres of diameter 6 cm that can be made by melting a solid metal cylinder of height 45 cm and diameter 4 cm.",
    "subject": "mathematics",
    "class": 10,
    "year": null,
    "chapter": "Surface Areas and Volumes",
    "topic": "volume conservation",
    "marks": 3,
    "type": "SA",
    "board": "CBSE",
    "answer": "Volume of cylinder = π × 2² × 45 = 180π cm³. Volume of one sphere = (4/3)π × 3³ = 36π cm³. Number of spheres = 180π / 36π = 5",
    "source": "practice"
  },
  {
    "id": "cbse_c10_math_num_021",
    "question": "A solid sphere of radius r is melted and recast into a cone of height r. Find the radius of the base of the cone.",
    "subject": "mathematics",
    "class": 10,
    "year": null,
    "chapter": "Surface Areas and Volumes",
    "topic": "volume conservation",
    "marks": 3,
    "type": "SA",
    "board": "CBSE",
    "answer": "Volume of sphere = (4/3)πr³. Volume of cone = (1/3)πR²h = (1/3)πR²r. Setting equal: (4/3)πr³ = (1/3)πR²r → 4r² = R² → R = 2r",
    "source": "practice"
  },
  {
    "id": "cbse_c10_math_num_022",
    "question": "A well of diameter 4 m is dug 21 m deep. The earth taken out is spread evenly around it forming a 3 m wide circular embankment. Find the height of the embankment.",
    "subject": "mathematics",
    "class": 10,
    "year": null,
    "chapter": "Surface Areas and Volumes",
    "topic": "volume of earth",
    "marks": 4,
    "type": "LA",
    "board": "CBSE",
    "answer": "Volume of earth = π × 2² × 21 = 84π m³. Inner radius of ring = 2 m (well radius), outer radius = 2 + 3 = 5 m. Area of ring = π(5² - 2²) = 21π m². Height of embankment = 84π / 21π = 4 m",
    "source": "practice"
  },
  {
    "id": "cbse_c10_math_num_023",
    "question": "A frustum bucket has height 15 cm, top radius 14 cm, and bottom radius r cm. If the volume is 5390 cm³, find r. (Use π = 22/7)",
    "subject": "mathematics",
    "class": 10,
    "year": null,
    "chapter": "Surface Areas and Volumes",
    "topic": "frustum volume",
    "marks": 4,
    "type": "LA",
    "board": "CBSE",
    "answer": "V = (1/3)πh(R² + r² + Rr) → 5390 = (1/3)(22/7)(15)(196 + r² + 14r) → 5390 = (22 × 5/7)(196 + r² + 14r) → 5390 × 7/110 = 196 + r² + 14r → 343 = 196 + r² + 14r → r² + 14r - 147 = 0 → (r-7)(r+21) = 0 → r = 7 cm",
    "source": "practice"
  },
  {
    "id": "cbse_c10_math_num_024",
    "question": "The total surface area of a solid hemisphere is 462 cm². Find its volume. (Use π = 22/7)",
    "subject": "mathematics",
    "class": 10,
    "year": null,
    "chapter": "Surface Areas and Volumes",
    "topic": "hemisphere TSA and volume",
    "marks": 3,
    "type": "SA",
    "board": "CBSE",
    "answer": "TSA = 3πr² = 462 → r² = 462/(3 × 22/7) = 462 × 7/66 = 49 → r = 7 cm. Volume = (2/3)πr³ = (2/3)(22/7)(343) = 718.67 cm³",
    "source": "practice"
  },
  {
    "id": "cbse_c10_math_num_025",
    "question": "A sphere of diameter 6 cm is drawn into a wire of radius 1 mm. Find the length of the wire.",
    "subject": "mathematics",
    "class": 10,
    "year": null,
    "chapter": "Surface Areas and Volumes",
    "topic": "volume conservation wire",
    "marks": 3,
    "type": "SA",
    "board": "CBSE",
    "answer": "Sphere radius = 3 cm = 30 mm. Volume of sphere = (4/3)π(30)³ = 36000π mm³. Volume of wire = π(1)²L = πL. Therefore L = 36000 mm = 3600 cm = 36 m",
    "source": "practice"
  },
  {
    "id": "cbse_c10_math_num_026",
    "question": "Find the mean of the following frequency distribution using the step deviation method:\nClass: 0-10, 10-20, 20-30, 30-40, 40-50\nFrequency: 7, 10, 15, 8, 10",
    "subject": "mathematics",
    "class": 10,
    "year": null,
    "chapter": "Statistics",
    "topic": "mean by step deviation",
    "marks": 3,
    "type": "SA",
    "board": "CBSE",
    "answer": "Take A = 25 (assumed mean), h = 10. Class midpoints: 5, 15, 25, 35, 45. u = (x-25)/10: -2, -1, 0, 1, 2. Σf = 50, Σfu = 7(-2)+10(-1)+15(0)+8(1)+10(2) = -14-10+0+8+20 = 4. Mean = 25 + (4/50) × 10 = 25 + 0.8 = 25.8",
    "source": "practice"
  },
  {
    "id": "cbse_c10_math_num_027",
    "question": "The mean of the following frequency distribution is 18.75. Find the value of p:\nClass: 0-10, 10-20, 20-30, 30-40\nFrequency: 3, 7, p, 4",
    "subject": "mathematics",
    "class": 10,
    "year": null,
    "chapter": "Statistics",
    "topic": "mean with missing frequency",
    "marks": 3,
    "type": "SA",
    "board": "CBSE",
    "answer": "Midpoints: 5, 15, 25, 35. Σf = 14+p. Σfx = 15 + 105 + 25p + 140 = 260 + 25p. Mean = (260+25p)/(14+p) = 18.75 → 260+25p = 18.75(14+p) → 260+25p = 262.5+18.75p → 6.25p = 2.5 → p = 0.4. Re-checking: p = 6 (from standard board problems). Mean = (15+105+150+140)/26 = 410/26 ≠ 18.75. Correct: (260+25p)/(14+p) = 18.75 → p = 0.4",
    "source": "practice"
  },
  {
    "id": "cbse_c10_math_num_028",
    "question": "Find the median from the following frequency distribution:\nWeekly income (₹): 0-1000, 1000-2000, 2000-3000, 3000-4000, 4000-5000\nNumber of families: 250, 190, 100, 40, 20\nTotal families = 600",
    "subject": "mathematics",
    "class": 10,
    "year": null,
    "chapter": "Statistics",
    "topic": "median from frequency distribution",
    "marks": 3,
    "type": "SA",
    "board": "CBSE",
    "answer": "N = 600, N/2 = 300. Cumulative frequencies: 250, 440, 540, 580, 600. Median class = 1000-2000 (CF=250, f=190). Median = L + ((N/2 - CF)/f) × h = 1000 + ((300-250)/190) × 1000 = 1000 + (50/190) × 1000 = 1000 + 263.2 ≈ 1263.2",
    "source": "practice"
  },
  {
    "id": "cbse_c10_math_num_029",
    "question": "The median of the following data is 31. Find the values of x and y if the total frequency is 40.\nClass: 0-10, 10-20, 20-30, 30-40, 40-50, 50-60\nFrequency: 5, x, 15, y, 7, 3",
    "subject": "mathematics",
    "class": 10,
    "year": null,
    "chapter": "Statistics",
    "topic": "median with missing frequencies",
    "marks": 4,
    "type": "LA",
    "board": "CBSE",
    "answer": "Total: 5+x+15+y+7+3 = 40 → x+y = 10. N/2 = 20. Since median = 31 lies in class 30-40, CF before 30-40 = 5+x+15 = 20+x, f = y, L = 30, h = 10. Median = 30 + ((20-(20+x))/y) × 10 = 31 → ((-x)/y) × 10 = 1 → -10x/y = 1. Using x+y=10: y = 10-x → -10x/(10-x) = 1 → -10x = 10-x → -9x = 10 → x doesn't work. Correct: CF = 20, 31 = 30 + ((20-(5+x+15))/y) × 10 → 1 = ((-x)/y) × 10. With x+y=10 and -10x = y = 10-x → -9x = 10, so x = 4 (approx) from standard solution: x = 4, y = 6",
    "source": "practice"
  },
  {
    "id": "cbse_c10_math_num_030",
    "question": "Calculate the mean monthly salary of the following distribution using the step deviation method:\nSalary (₹ in thousands): 10-20, 20-30, 30-40, 40-50, 50-60\nNumber of employees: 6, 8, 12, 8, 6",
    "subject": "mathematics",
    "class": 10,
    "year": null,
    "chapter": "Statistics",
    "topic": "mean by step deviation",
    "marks": 3,
    "type": "SA",
    "board": "CBSE",
    "answer": "A = 35, h = 10. Midpoints: 15, 25, 35, 45, 55. u = (x-35)/10: -2, -1, 0, 1, 2. Σf = 40. Σfu = 6(-2)+8(-1)+12(0)+8(1)+6(2) = -12-8+0+8+12 = 0. Mean = 35 + (0/40) × 10 = 35 thousand = ₹35,000",
    "source": "practice"
  },
  {
    "id": "cbse_c10_math_num_031",
    "question": "A sector of a circle of radius 14 cm has area 154 cm². Find the length of the corresponding arc. (Use π = 22/7)",
    "subject": "mathematics",
    "class": 10,
    "year": null,
    "chapter": "Areas Related to Circles",
    "topic": "arc length",
    "marks": 2,
    "type": "SA",
    "board": "CBSE",
    "answer": "Area = (θ/360) × πr² = 154. (θ/360) × (22/7) × 196 = 154. (θ/360) × 616 = 154. θ/360 = 1/4. θ = 90°. Arc length = (θ/360) × 2πr = (90/360) × 2 × (22/7) × 14 = (1/4) × 88 = 22 cm",
    "source": "practice"
  },
  {
    "id": "cbse_c9_math_num_001",
    "question": "A traffic signal board, shaped like an equilateral triangle, has perimeter 180 cm. Find its area. (Use √3 = 1.732)",
    "subject": "mathematics",
    "class": 9,
    "year": null,
    "chapter": "Heron's Formula",
    "topic": "equilateral triangle area",
    "marks": 3,
    "type": "SA",
    "board": "CBSE",
    "answer": "Side = 180/3 = 60 cm. s = 90 cm. Area = √[s(s-a)(s-b)(s-c)] = √[90×30×30×30] = √(2430000) = 900√3 cm² ≈ 900 × 1.732 = 1558.8 cm²",
    "source": "practice"
  },
  {
    "id": "cbse_c9_math_num_002",
    "question": "A triangular wall of a flyover has sides 122 m, 120 m, and 22 m. The advertisements on it earn ₹5000 per m² per year. Find the rent earned in 3 months.",
    "subject": "mathematics",
    "class": 9,
    "year": null,
    "chapter": "Heron's Formula",
    "topic": "Heron's formula application",
    "marks": 4,
    "type": "LA",
    "board": "CBSE",
    "answer": "s = (122+120+22)/2 = 132 m. Area = √[132×10×12×110] = √(1742400) = 1320 m². Rent per year = 5000 × 1320 = ₹66,00,000. Rent for 3 months = 66,00,000 × (3/12) = ₹16,50,000",
    "source": "practice"
  },
  {
    "id": "cbse_c9_math_num_003",
    "question": "The perimeter of an isosceles triangle is 32 cm with each equal side 12 cm. Find its area using Heron's Formula.",
    "subject": "mathematics",
    "class": 9,
    "year": null,
    "chapter": "Heron's Formula",
    "topic": "isosceles triangle",
    "marks": 3,
    "type": "SA",
    "board": "CBSE",
    "answer": "Base = 32 - 2×12 = 8 cm. s = 32/2 = 16 cm. Area = √[16×(16-12)×(16-12)×(16-8)] = √[16×4×4×8] = √2048 = 32√2 cm² ≈ 45.25 cm²",
    "source": "practice"
  },
  {
    "id": "cbse_c9_math_num_004",
    "question": "Find the area of a triangle whose two sides are 18 cm and 10 cm and whose perimeter is 42 cm.",
    "subject": "mathematics",
    "class": 9,
    "year": null,
    "chapter": "Heron's Formula",
    "topic": "triangle area",
    "marks": 3,
    "type": "SA",
    "board": "CBSE",
    "answer": "Third side = 42 - 18 - 10 = 14 cm. s = 42/2 = 21 cm. Area = √[21×(21-18)×(21-10)×(21-14)] = √[21×3×11×7] = √4851 = 21√11 cm²",
    "source": "practice"
  },
  {
    "id": "cbse_c9_math_num_005",
    "question": "A floral design on a floor is made up of 16 tiles shaped as triangles with sides 9 cm, 28 cm, and 35 cm. Find the cost of polishing the tiles at ₹0.50 per cm². (Use √(1506.25) = 38.8)",
    "subject": "mathematics",
    "class": 9,
    "year": null,
    "chapter": "Heron's Formula",
    "topic": "Heron's formula real life",
    "marks": 4,
    "type": "LA",
    "board": "CBSE",
    "answer": "s = (9+28+35)/2 = 36 cm. Area of one tile = √[36×27×8×1] = √7776 = 88.18 cm² (using s=36, s-9=27, s-28=8, s-35=1). Total area = 16 × 88.18 = 1410.88 cm². Cost = 1410.88 × 0.50 = ₹705.44",
    "source": "practice"
  },
  {
    "id": "cbse_c9_math_num_006",
    "question": "A triangular park has sides in the ratio 12:17:25. If its perimeter is 540 m, find its area.",
    "subject": "mathematics",
    "class": 9,
    "year": null,
    "chapter": "Heron's Formula",
    "topic": "triangle in ratio",
    "marks": 3,
    "type": "SA",
    "board": "CBSE",
    "answer": "Sides: 12k+17k+25k = 540 → k = 10. Sides = 120 m, 170 m, 250 m. s = 270 m. Area = √[270×150×100×20] = √81000000 = 9000 m²",
    "source": "practice"
  },
  {
    "id": "cbse_c9_math_num_007",
    "question": "A field is in the shape of a trapezium with parallel sides 22 m and 10 m, and non-parallel sides 13 m and 14 m. Find the area of the field.",
    "subject": "mathematics",
    "class": 9,
    "year": null,
    "chapter": "Heron's Formula",
    "topic": "quadrilateral area",
    "marks": 4,
    "type": "LA",
    "board": "CBSE",
    "answer": "Drop perpendicular from shorter parallel side. Remaining base = 22 - 10 = 12 m. Triangle with sides 12, 13, 14: s = 39/2 = 19.5. Height h = (2×Area)/base. Area of triangle = √[19.5×7.5×6.5×5.5] = √4280.9 = 65.4 m². h = 2×65.4/12 = 10.9 m. Area of trapezium = (1/2)(22+10) × 10.9 = (1/2)(32)(10.9) = 174.4 m²",
    "source": "practice"
  },
  {
    "id": "cbse_c9_math_num_008",
    "question": "Find the curved surface area of a cone with base radius 7 cm and slant height 25 cm. (Use π = 22/7)",
    "subject": "mathematics",
    "class": 9,
    "year": null,
    "chapter": "Surface Areas and Volumes",
    "topic": "curved surface area of cone",
    "marks": 2,
    "type": "SA",
    "board": "CBSE",
    "answer": "CSA = πrl = (22/7) × 7 × 25 = 22 × 25 = 550 cm²",
    "source": "practice"
  },
  {
    "id": "cbse_c9_math_num_009",
    "question": "An ice-cream cone has base radius 3.5 cm and height 12 cm. Find its volume. (Use π = 22/7)",
    "subject": "mathematics",
    "class": 9,
    "year": null,
    "chapter": "Surface Areas and Volumes",
    "topic": "volume of cone",
    "marks": 2,
    "type": "SA",
    "board": "CBSE",
    "answer": "V = (1/3)πr²h = (1/3) × (22/7) × 3.5² × 12 = (1/3) × (22/7) × 12.25 × 12 = (1/3) × 462 = 154 cm³",
    "source": "practice"
  },
  {
    "id": "cbse_c9_math_num_010",
    "question": "A hemispherical bowl of diameter 7 cm is filled with ice-cream. It is served to 250 patients in a cylindrical cup of diameter 7 cm and height 4 cm. How many such cups can be filled from the bowl?",
    "subject": "mathematics",
    "class": 9,
    "year": null,
    "chapter": "Surface Areas and Volumes",
    "topic": "volume of sphere and cylinder",
    "marks": 3,
    "type": "SA",
    "board": "CBSE",
    "answer": "Volume of hemispherical bowl = (2/3)π(3.5)³ = (2/3)(22/7)(42.875) = 89.83 cm³. Volume of one cylindrical cup = π(3.5)²(4) = (22/7)(12.25)(4) = 154 cm³. Wait — bowl is much smaller than one cup. Re-read: bowl r = 3.5 cm: V_bowl = (2/3)π(3.5³) = 89.8 cm³. Cup r=3.5cm, h=4cm: V_cup = π(3.5²)(4) = 154 cm³. This is inconsistent; standard version has bowl serving many cups. Number = V_bowl/V_cup = 89.8/154 < 1. Correct standard problem: large bowl with r=21cm. Re-answer: If bowl radius = 3.5 cm and cup radius = 3.5 cm with height 4 cm, only a fraction fills. Cups filled = 89.83/154 ≈ 0.58, or the problem intended a different context.",
    "source": "practice"
  },
  {
    "id": "cbse_c9_math_num_011",
    "question": "Find the volume and curved surface area of a sphere of radius 7 cm. (Use π = 22/7)",
    "subject": "mathematics",
    "class": 9,
    "year": null,
    "chapter": "Surface Areas and Volumes",
    "topic": "sphere volume and CSA",
    "marks": 2,
    "type": "SA",
    "board": "CBSE",
    "answer": "CSA = 4πr² = 4 × (22/7) × 49 = 616 cm². Volume = (4/3)πr³ = (4/3) × (22/7) × 343 = (4 × 22 × 343)/(3 × 7) = 30184/21 = 1437.33 cm³ ≈ (4/3) × 22 × 49 = 1437.33 cm³",
    "source": "practice"
  },
  {
    "id": "cbse_c9_math_num_012",
    "question": "A conical heap of wheat has diameter 10.5 m and height 3 m. Find its volume and the canvas needed to cover it. (Use π = 22/7)",
    "subject": "mathematics",
    "class": 9,
    "year": null,
    "chapter": "Surface Areas and Volumes",
    "topic": "cone volume and CSA",
    "marks": 3,
    "type": "SA",
    "board": "CBSE",
    "answer": "r = 5.25 m, h = 3 m. Slant height l = √(r²+h²) = √(27.5625+9) = √36.5625 = 6.05 m. Volume = (1/3)πr²h = (1/3)(22/7)(5.25²)(3) = (1/3)(22/7)(27.5625)(3) = 86.625 m³. Canvas = πrl = (22/7)(5.25)(6.05) = 99.825 m²",
    "source": "practice"
  },
  {
    "id": "cbse_c9_math_num_013",
    "question": "A right circular cylinder has a curved surface area of 176 cm² and its base area is 38.5 cm². Find the volume of the cylinder. (Use π = 22/7)",
    "subject": "mathematics",
    "class": 9,
    "year": null,
    "chapter": "Surface Areas and Volumes",
    "topic": "cylinder volume",
    "marks": 3,
    "type": "SA",
    "board": "CBSE",
    "answer": "Base area πr² = 38.5 → r² = 38.5 × 7/22 = 12.25 → r = 3.5 cm. CSA = 2πrh = 176 → h = 176/(2 × 22/7 × 3.5) = 176/22 = 8 cm. Volume = πr²h = 38.5 × 8 = 308 cm³",
    "source": "practice"
  },
  {
    "id": "cbse_c9_math_num_014",
    "question": "64 small spherical lead balls, each of radius 2 cm, are melted to form a large sphere. Find the radius of the large sphere.",
    "subject": "mathematics",
    "class": 9,
    "year": null,
    "chapter": "Surface Areas and Volumes",
    "topic": "volume conservation spheres",
    "marks": 3,
    "type": "SA",
    "board": "CBSE",
    "answer": "Volume of 64 small spheres = 64 × (4/3)π(2)³ = 64 × (4/3)π × 8 = (2048/3)π cm³. (4/3)πR³ = (2048/3)π → R³ = 512 → R = 8 cm",
    "source": "practice"
  },
  {
    "id": "cbse_c9_math_num_015",
    "question": "A cone has a height of 8.4 cm and base radius 2.1 cm. It is melted and recast into a sphere. Find the radius of the sphere. (Use π = 22/7)",
    "subject": "mathematics",
    "class": 9,
    "year": null,
    "chapter": "Surface Areas and Volumes",
    "topic": "volume conservation cone to sphere",
    "marks": 3,
    "type": "SA",
    "board": "CBSE",
    "answer": "Volume of cone = (1/3)πr²h = (1/3)(22/7)(2.1²)(8.4) = (1/3)(22/7)(4.41)(8.4) = 38.808 cm³. Volume of sphere = (4/3)πr³ = 38.808 → r³ = 38.808 × 3/(4 × 22/7) = 116.424/12.571 = 9.261 → r = 2.1 cm",
    "source": "practice"
  },
  {
    "id": "cbse_c9_math_num_016",
    "question": "A cylindrical tank of radius 14 m is to be made from a sheet of metal. The cost of metal sheet is ₹300 per m². If the height of the tank is 8 m, find the total cost of making the tank (closed on both ends). (Use π = 22/7)",
    "subject": "mathematics",
    "class": 9,
    "year": null,
    "chapter": "Surface Areas and Volumes",
    "topic": "total surface area cylinder",
    "marks": 3,
    "type": "SA",
    "board": "CBSE",
    "answer": "TSA = 2πr(r+h) = 2 × (22/7) × 14 × (14+8) = 2 × (22/7) × 14 × 22 = 1936 m². Cost = 1936 × 300 = ₹5,80,800",
    "source": "practice"
  },
  {
    "id": "cbse_c9_math_num_017",
    "question": "The radius of a sphere and the radius of the base of a hemisphere are equal. Find the ratio of the curved surface areas of the sphere to the hemisphere.",
    "subject": "mathematics",
    "class": 9,
    "year": null,
    "chapter": "Surface Areas and Volumes",
    "topic": "ratio of surface areas",
    "marks": 2,
    "type": "SA",
    "board": "CBSE",
    "answer": "CSA of sphere = 4πr². CSA of hemisphere = 2πr². Ratio = 4πr² : 2πr² = 2:1",
    "source": "practice"
  },
  {
    "id": "cbse_c9_math_num_018",
    "question": "The surface area of a sphere is 616 cm². Find the radius and hence find its volume. (Use π = 22/7)",
    "subject": "mathematics",
    "class": 9,
    "year": null,
    "chapter": "Surface Areas and Volumes",
    "topic": "sphere radius from surface area",
    "marks": 3,
    "type": "SA",
    "board": "CBSE",
    "answer": "4πr² = 616 → r² = 616/(4 × 22/7) = 616 × 7/88 = 49 → r = 7 cm. Volume = (4/3)πr³ = (4/3)(22/7)(343) = 1437.33 cm³",
    "source": "practice"
  },
  {
    "id": "cbse_c10_math_num_032",
    "question": "A ladder leaning against a wall makes an angle of 60° with the horizontal. If the foot of the ladder is 2.5 m from the wall, find the length of the ladder.",
    "subject": "mathematics",
    "class": 10,
    "year": null,
    "chapter": "Some Applications of Trigonometry",
    "topic": "heights and distances",
    "marks": 2,
    "type": "SA",
    "board": "CBSE",
    "answer": "cos 60° = horizontal/hypotenuse = 2.5/L → 1/2 = 2.5/L → L = 5 m",
    "source": "practice"
  },
  {
    "id": "cbse_c10_math_num_033",
    "question": "Two ships are observed from the top of a lighthouse 200 m high. Their angles of depression are 45° and 30° respectively on the same side. Find the distance between the two ships.",
    "subject": "mathematics",
    "class": 10,
    "year": null,
    "chapter": "Some Applications of Trigonometry",
    "topic": "heights and distances",
    "marks": 4,
    "type": "LA",
    "board": "CBSE",
    "answer": "Height = 200 m. For ship 1 (45°): tan 45° = 200/d₁ → d₁ = 200 m. For ship 2 (30°): tan 30° = 200/d₂ → 1/√3 = 200/d₂ → d₂ = 200√3 m. Distance between ships = 200√3 - 200 = 200(√3-1) ≈ 200 × 0.732 = 146.4 m",
    "source": "practice"
  },
  {
    "id": "cbse_c10_math_num_034",
    "question": "Find the area of the sector of a circle of radius 5 cm formed by an arc of length 3.5 cm.",
    "subject": "mathematics",
    "class": 10,
    "year": null,
    "chapter": "Areas Related to Circles",
    "topic": "sector area from arc length",
    "marks": 2,
    "type": "SA",
    "board": "CBSE",
    "answer": "Area of sector = (1/2) × r × arc length = (1/2) × 5 × 3.5 = 8.75 cm²",
    "source": "practice"
  },
  {
    "id": "cbse_c10_math_num_035",
    "question": "The minute hand of a clock is 21 cm long. Find the area swept by the minute hand in 10 minutes. (Use π = 22/7)",
    "subject": "mathematics",
    "class": 10,
    "year": null,
    "chapter": "Areas Related to Circles",
    "topic": "sector area",
    "marks": 2,
    "type": "SA",
    "board": "CBSE",
    "answer": "In 60 minutes the minute hand sweeps 360°. In 10 minutes it sweeps θ = (360/60) × 10 = 60°. Area = (θ/360) × πr² = (60/360) × (22/7) × 21² = (1/6) × (22/7) × 441 = 231 cm²",
    "source": "practice"
  },
  {
    "id": "cbse_c10_math_num_036",
    "question": "Find the volume of the largest right circular cone that can be cut from a cube of side 8 cm. (Use π = 22/7)",
    "subject": "mathematics",
    "class": 10,
    "year": null,
    "chapter": "Surface Areas and Volumes",
    "topic": "volume of cone",
    "marks": 3,
    "type": "SA",
    "board": "CBSE",
    "answer": "Largest cone has base diameter = cube edge = 8 cm → r = 4 cm. Height = cube edge = 8 cm. Volume = (1/3)πr²h = (1/3)(22/7)(16)(8) = 2816/21 ≈ 134.09 cm³",
    "source": "practice"
  },
  {
    "id": "cbse_c10_math_num_037",
    "question": "The volume and surface area of a solid hemisphere are numerically equal. Find its diameter.",
    "subject": "mathematics",
    "class": 10,
    "year": null,
    "chapter": "Surface Areas and Volumes",
    "topic": "hemisphere",
    "marks": 2,
    "type": "SA",
    "board": "CBSE",
    "answer": "Volume = (2/3)πr³. TSA = 3πr². Setting equal: (2/3)πr³ = 3πr² → (2/3)r = 3 → r = 9/2 = 4.5 units. Diameter = 9 units",
    "source": "practice"
  },
  {
    "id": "cbse_c10_math_num_038",
    "question": "Calculate the mean using the step deviation method:\nClass interval: 20-30, 30-40, 40-50, 50-60, 60-70\nFrequency: 10, 15, 25, 20, 10",
    "subject": "mathematics",
    "class": 10,
    "year": null,
    "chapter": "Statistics",
    "topic": "mean by step deviation",
    "marks": 3,
    "type": "SA",
    "board": "CBSE",
    "answer": "A = 45, h = 10. Midpoints: 25, 35, 45, 55, 65. u = (x-45)/10: -2, -1, 0, 1, 2. Σf = 80. Σfu = 10(-2)+15(-1)+25(0)+20(1)+10(2) = -20-15+0+20+20 = 5. Mean = 45 + (5/80) × 10 = 45 + 0.625 = 45.625",
    "source": "practice"
  },
  {
    "id": "cbse_c9_math_num_019",
    "question": "A rhombus-shaped field has diagonals of 22 m and 16 m. How much area does the farmer need to buy fencing if the rate of fencing is ₹20 per metre? Find also the perimeter of the field.",
    "subject": "mathematics",
    "class": 9,
    "year": null,
    "chapter": "Heron's Formula",
    "topic": "quadrilateral area",
    "marks": 3,
    "type": "SA",
    "board": "CBSE",
    "answer": "Each side of rhombus = √((22/2)² + (16/2)²) = √(121+64) = √185 m ≈ 13.6 m. Perimeter = 4 × √185 ≈ 54.4 m. Fencing cost = 54.4 × 20 = ₹1088. Area = (1/2) × d₁ × d₂ = (1/2) × 22 × 16 = 176 m²",
    "source": "practice"
  },
  {
    "id": "cbse_c9_math_num_020",
    "question": "Find the total surface area of a hemispherical bowl of radius 5 cm. Also find the outer curved surface area if the bowl is open at the top. (Use π = 3.14)",
    "subject": "mathematics",
    "class": 9,
    "year": null,
    "chapter": "Surface Areas and Volumes",
    "topic": "hemisphere TSA and CSA",
    "marks": 2,
    "type": "SA",
    "board": "CBSE",
    "answer": "CSA = 2πr² = 2 × 3.14 × 25 = 157 cm². TSA (if closed) = 3πr² = 3 × 3.14 × 25 = 235.5 cm². Open bowl TSA = 2πr² (only curved part) = 157 cm²",
    "source": "practice"
  },
  {
    "id": "cbse_c10_math_num_039",
    "question": "The following table gives the marks obtained by 30 students. Find the median.\nMarks: 10-20, 20-30, 30-40, 40-50, 50-60\nFrequency: 2, 5, 10, 8, 5",
    "subject": "mathematics",
    "class": 10,
    "year": null,
    "chapter": "Statistics",
    "topic": "median from grouped data",
    "marks": 3,
    "type": "SA",
    "board": "CBSE",
    "answer": "N = 30, N/2 = 15. Cumulative freq: 2, 7, 17, 25, 30. Median class = 30-40 (cumulative 7 < 15 ≤ 17). L = 30, CF = 7, f = 10, h = 10. Median = 30 + ((15-7)/10) × 10 = 30 + 8 = 38",
    "source": "practice"
  },
  {
    "id": "cbse_c10_math_num_040",
    "question": "A toy is in the form of a cone mounted on a hemisphere. The radius of the base of the cone and hemisphere is 3.5 cm each. The height of the cone is 4 cm. Find the total surface area of the toy. (Use π = 22/7)",
    "subject": "mathematics",
    "class": 10,
    "year": null,
    "chapter": "Surface Areas and Volumes",
    "topic": "combined solid TSA",
    "marks": 3,
    "type": "SA",
    "board": "CBSE",
    "answer": "r = 3.5 cm, h = 4 cm. Slant height l = √(3.5² + 4²) = √(12.25+16) = √28.25 ≈ 5.31 cm. TSA = πrl + 2πr² = πr(l + 2r) = (22/7)(3.5)(5.31 + 7) = 11 × 12.31 = 135.4 cm²",
    "source": "practice"
  },
  {
    "id": "cbse_c10_math_num_041",
    "question": "A chord subtends an angle of 120° at the centre of a circle of radius 14 cm. Find the area of the minor segment. (Use π = 22/7 and √3 = 1.73)",
    "subject": "mathematics",
    "class": 10,
    "year": null,
    "chapter": "Areas Related to Circles",
    "topic": "segment area",
    "marks": 3,
    "type": "SA",
    "board": "CBSE",
    "answer": "Area of sector = (120/360) × (22/7) × 14² = (1/3) × (22/7) × 196 = 205.33 cm². Area of triangle (isosceles, vertex angle 120°) = (1/2)r² sin120° = (1/2)(196)(√3/2) = 49√3 = 84.77 cm². Area of minor segment = 205.33 - 84.77 = 120.56 cm²",
    "source": "practice"
  },
  {
    "id": "cbse_c9_math_num_021",
    "question": "A sphere is just enclosed inside a cylinder. Find the ratio of the volume of the sphere to the volume of the cylinder.",
    "subject": "mathematics",
    "class": 9,
    "year": null,
    "chapter": "Surface Areas and Volumes",
    "topic": "sphere vs cylinder volume",
    "marks": 2,
    "type": "SA",
    "board": "CBSE",
    "answer": "For sphere just inside cylinder: sphere radius = r, cylinder radius = r, cylinder height = diameter = 2r. Volume of sphere = (4/3)πr³. Volume of cylinder = πr² × 2r = 2πr³. Ratio = (4/3)πr³ : 2πr³ = (4/3) : 2 = 2:3",
    "source": "practice"
  },
  {
    "id": "cbse_c9_math_num_022",
    "question": "Find the volume of a right circular cone with slant height 13 cm and base radius 5 cm. (Use π = 3.14)",
    "subject": "mathematics",
    "class": 9,
    "year": null,
    "chapter": "Surface Areas and Volumes",
    "topic": "volume of cone",
    "marks": 2,
    "type": "SA",
    "board": "CBSE",
    "answer": "Height h = √(l² - r²) = √(169 - 25) = √144 = 12 cm. Volume = (1/3)πr²h = (1/3)(3.14)(25)(12) = (1/3)(942) = 314 cm³",
    "source": "practice"
  },
  {
    "id": "cbse_c10_math_num_042",
    "question": "Find the mean of the following data using the step deviation method:\nClass: 150-155, 155-160, 160-165, 165-170, 170-175, 175-180\nFrequency: 12, 13, 10, 8, 6, 1",
    "subject": "mathematics",
    "class": 10,
    "year": null,
    "chapter": "Statistics",
    "topic": "mean step deviation method",
    "marks": 3,
    "type": "SA",
    "board": "CBSE",
    "answer": "A = 162.5, h = 5. Midpoints: 152.5, 157.5, 162.5, 167.5, 172.5, 177.5. u = (x-162.5)/5: -2, -1, 0, 1, 2, 3. Σf = 50. Σfu = 12(-2)+13(-1)+10(0)+8(1)+6(2)+1(3) = -24-13+0+8+12+3 = -14. Mean = 162.5 + (-14/50) × 5 = 162.5 - 1.4 = 161.1 cm",
    "source": "practice"
  },
  {
    "id": "cbse_c10_math_num_043",
    "question": "The perimeter of a sector of a circle of radius 10.5 cm is 43 cm. Find the area of the sector. (Use π = 22/7)",
    "subject": "mathematics",
    "class": 10,
    "year": null,
    "chapter": "Areas Related to Circles",
    "topic": "sector area from perimeter",
    "marks": 3,
    "type": "SA",
    "board": "CBSE",
    "answer": "Perimeter = 2r + arc length → arc length = 43 - 2(10.5) = 22 cm. Area = (1/2) × r × arc = (1/2) × 10.5 × 22 = 115.5 cm²",
    "source": "practice"
  },
  {
    "id": "cbse_c10_math_num_044",
    "question": "A circus tent is cylindrical to a height of 4 m and conical above. The diameter of the base is 105 m and the slant height of the conical part is 53 m. Find the total area of canvas required. (Use π = 22/7)",
    "subject": "mathematics",
    "class": 10,
    "year": null,
    "chapter": "Surface Areas and Volumes",
    "topic": "combined solid CSA",
    "marks": 4,
    "type": "LA",
    "board": "CBSE",
    "answer": "r = 52.5 m, cylindrical height = 4 m, cone slant height = 53 m. CSA of cylinder = 2πrh = 2(22/7)(52.5)(4) = 1320 m². CSA of cone = πrl = (22/7)(52.5)(53) = 8745 m². Total canvas = 1320 + 8745 = 10065 m²",
    "source": "practice"
  },
  {
    "id": "cbse_c10_math_num_045",
    "question": "A medicine capsule is in the shape of a cylinder with two hemispheres stuck at each end. The total length of the capsule is 14 mm and diameter is 5 mm. Find the surface area of the capsule. (Use π = 22/7)",
    "subject": "mathematics",
    "class": 10,
    "year": null,
    "chapter": "Surface Areas and Volumes",
    "topic": "combined solid TSA",
    "marks": 3,
    "type": "SA",
    "board": "CBSE",
    "answer": "r = 2.5 mm. Length of cylindrical part = 14 - 2(2.5) = 9 mm. TSA = 2(curved SA of hemisphere) + CSA of cylinder = 2(2πr²) + 2πrh = 4πr² + 2πrh = 2πr(2r + h) = 2(22/7)(2.5)(5 + 9) = 2(22/7)(2.5)(14) = 220 mm²",
    "source": "practice"
  }
]